torch_deterministic/__init__.py
torch_deterministic/batch_rng.py
torch_deterministic/infinite_sampler.py
torch_deterministic-0.1.0.dist-info/WHEEL
torch_deterministic-0.1.0.dist-info/METADATA
torch_deterministic-0.1.0.dist-info/RECORD
