Metadata-Version: 2.3
Name: torch_deterministic
Version: 0.1.0
Summary: Tools for making reproducible PyTorch datasets
Author-email: Kale Kundert <kale@thekunderts.net>
Requires-Python: ~=3.8
Classifier: Programming Language :: Python :: 3
Requires-Dist: more_itertools
Requires-Dist: numpy
Requires-Dist: reprfunc
Requires-Dist: torch
Requires-Dist: sphinx ; extra == "doc"
Requires-Dist: sphinx_rtd_theme ; extra == "doc"
Requires-Dist: myst_parser ; extra == "doc"
Requires-Dist: autoclasstoc ; extra == "doc"
Requires-Dist: pytest ; extra == "test"
Requires-Dist: parametrize_from_file ; extra == "test"
Project-URL: Bug Tracker, https://github.com/kalekundert/torch_deterministic/issues
Project-URL: Continuous Integration, https://github.com/kalekundert/torch_deterministic/actions
Project-URL: Documentation, https://torch-deterministic.readthedocs.io/en/latest/
Project-URL: Test Coverage, https://app.codecov.io/github/kalekundert/torch_deterministic
Project-URL: Version Control, https://github.com/kalekundert/torch_deterministic
Provides-Extra: doc
Provides-Extra: test
